Pytorch04ZhongwenWendang/README.md
Pytorch04ZhongwenWendang/__init__.py
Pytorch04ZhongwenWendang/__main__.py
Pytorch04ZhongwenWendang/file.epub
Pytorch04ZhongwenWendang/index.html
Pytorch04ZhongwenWendang/css/__init__.py
Pytorch04ZhongwenWendang/css/annotations.css
Pytorch04ZhongwenWendang/css/main.css
Pytorch04ZhongwenWendang/css/normalize.css
Pytorch04ZhongwenWendang/css/popup.css
Pytorch04ZhongwenWendang/font/__init__.py
Pytorch04ZhongwenWendang/font/fontello.eot
Pytorch04ZhongwenWendang/font/fontello.svg
Pytorch04ZhongwenWendang/font/fontello.ttf
Pytorch04ZhongwenWendang/font/fontello.woff
Pytorch04ZhongwenWendang/img/__init__.py
Pytorch04ZhongwenWendang/img/annotator-glyph-sprite.png
Pytorch04ZhongwenWendang/img/annotator-icon-sprite.png
Pytorch04ZhongwenWendang/img/apple-touch-icon.png
Pytorch04ZhongwenWendang/img/cancelfullscreen.png
Pytorch04ZhongwenWendang/img/close.png
Pytorch04ZhongwenWendang/img/fullscreen.png
Pytorch04ZhongwenWendang/img/loader.gif
Pytorch04ZhongwenWendang/img/menu-icon.png
Pytorch04ZhongwenWendang/img/save.png
Pytorch04ZhongwenWendang/img/saved.png
Pytorch04ZhongwenWendang/img/settings-s.png
Pytorch04ZhongwenWendang/img/settings.png
Pytorch04ZhongwenWendang/img/star.png
Pytorch04ZhongwenWendang/js/__init__.py
Pytorch04ZhongwenWendang/js/epub.js
Pytorch04ZhongwenWendang/js/epub.min.js
Pytorch04ZhongwenWendang/js/epub.min.map
Pytorch04ZhongwenWendang/js/hooks.min.js
Pytorch04ZhongwenWendang/js/hooks.min.map
Pytorch04ZhongwenWendang/js/reader.js
Pytorch04ZhongwenWendang/js/reader.js.map
Pytorch04ZhongwenWendang/js/reader.min.js
Pytorch04ZhongwenWendang/js/reader.min.map
Pytorch04ZhongwenWendang/js/hooks/__init__.py
Pytorch04ZhongwenWendang/js/hooks/extensions/__init__.py
Pytorch04ZhongwenWendang/js/hooks/extensions/highlight.js
Pytorch04ZhongwenWendang/js/libs/__init__.py
Pytorch04ZhongwenWendang/js/libs/jquery.min.js
Pytorch04ZhongwenWendang/js/libs/localforage.min.js
Pytorch04ZhongwenWendang/js/libs/screenfull.js
pytorch_0_4_zhongwen_wendang-2024.3.5.0.dist-info/METADATA
pytorch_0_4_zhongwen_wendang-2024.3.5.0.dist-info/WHEEL
pytorch_0_4_zhongwen_wendang-2024.3.5.0.dist-info/entry_points.txt
pytorch_0_4_zhongwen_wendang-2024.3.5.0.dist-info/top_level.txt
pytorch_0_4_zhongwen_wendang-2024.3.5.0.dist-info/RECORD
